cdk_alexa_skill/__init__.py
cdk_alexa_skill/py.typed
cdk_alexa_skill/_jsii/__init__.py
cdk_alexa_skill/_jsii/cdk-alexa-skill@2.0.4.jsii.tgz
cdk_alexa_skill-2.0.4.dist-info/LICENSE
cdk_alexa_skill-2.0.4.dist-info/METADATA
cdk_alexa_skill-2.0.4.dist-info/WHEEL
cdk_alexa_skill-2.0.4.dist-info/top_level.txt
cdk_alexa_skill-2.0.4.dist-info/RECORD
